eric_sse/__init__.py
eric_sse/clients.py
eric_sse/connection.py
eric_sse/entities.py
eric_sse/exception.py
eric_sse/interfaces.py
eric_sse/listener.py
eric_sse/message.py
eric_sse/prefabs.py
eric_sse/queues.py
eric_sse/repository.py
eric_sse/servers.py
eric_sse-2.1.1.2.dist-info/LICENSE
eric_sse-2.1.1.2.dist-info/METADATA
eric_sse-2.1.1.2.dist-info/WHEEL
eric_sse-2.1.1.2.dist-info/RECORD
