Metadata-Version: 2.3
Name: eric-sse
Version: 2.1.1.2
Summary: A lightweight message dispatcher based on SSE protocol data transfer objects format
License: MIT
Keywords: server sent events,sse,queue,concurrency
Author: Luca Stretti
Author-email: laxertu@gmail.com
Requires-Python: >=3.10
Classifier: License :: OSI Approved :: MIT License
Classifier: Programming Language :: Python :: 3
Classifier: Programming Language :: Python :: 3.10
Classifier: Programming Language :: Python :: 3.11
Classifier: Programming Language :: Python :: 3.12
Classifier: Programming Language :: Python :: 3.13
Project-URL: Changelog, https://laxertu.github.io/eric/changelog.html
Project-URL: Documentation, https://laxertu.github.io/eric/docs.html
Project-URL: Homepage, https://laxertu.github.io/eric
Project-URL: Issues, https://github.com/laxertu/eric/issues
Project-URL: Repository, https://github.com/laxertu/eric
